pitop/pma/__init__.py
pitop/pma/adc_base.py
pitop/pma/button.py
pitop/pma/buzzer.py
pitop/pma/encoder_motor.py
pitop/pma/encoder_motor_controller.py
pitop/pma/imu.py
pitop/pma/imu_controller.py
pitop/pma/led.py
pitop/pma/light_sensor.py
pitop/pma/parameters.py
pitop/pma/plate_interface.py
pitop/pma/potentiometer.py
pitop/pma/servo_controller.py
pitop/pma/servo_motor.py
pitop/pma/sound_sensor.py
pitop/pma/ultrasonic_sensor.py
pitop/pma/ultrasonic_sensor_base.py
pitop/pma/common/__init__.py
pitop/pma/common/encoder_motor_registers.py
pitop/pma/common/imu_registers.py
pitop/pma/common/plate_registers.py
pitop/pma/common/servo_motor_registers.py
pitop/pma/common/ultrasonic_registers.py
pitop/pma/common/utils.py
pitop/pma/common/math_functions/__init__.py
pitop/pma/common/math_functions/ellipsoid_functions.py
pitop.pma-0.34.3.post1.dist-info/METADATA
pitop.pma-0.34.3.post1.dist-info/WHEEL
pitop.pma-0.34.3.post1.dist-info/top_level.txt
pitop.pma-0.34.3.post1.dist-info/RECORD
